{
  "applications": "*",
  "changelogDate": "20230326183542",
  "dto": "no",
  "embedded": false,
  "entityTableName": "league",
  "fields": [
    {
      "fieldName": "name",
      "fieldType": "String",
      "fieldValidateRules": ["minlength", "maxlength", "required"],
      "fieldValidateRulesMaxlength": "100",
      "fieldValidateRulesMinlength": "3"
    },
    {
      "fieldName": "description",
      "fieldType": "byte[]",
      "fieldTypeBlobContent": "text",
      "fieldValidateRules": ["required"]
    }
  ],
  "fluentMethods": true,
  "jpaMetamodelFiltering": false,
  "name": "League",
  "pagination": "pagination",
  "readOnly": false,
  "relationships": [
    {
      "otherEntityName": "profile",
      "otherEntityRelationshipName": "league",
      "relationshipName": "profile",
      "relationshipType": "one-to-many"
    }
  ],
  "service": "serviceImpl"
}
